ampgen/__init__.py
ampgen/model/Discriminator.py
ampgen/model/MICscorer.py
ampgen/model/__init__.py
ampgen/model/features.py
ampgen/model/train_discriminator.py
ampgen/model/iFeature/PseKRAAC/__init__.py
ampgen/model/iFeature/PseKRAAC/type1.py
ampgen/model/iFeature/PseKRAAC/type10.py
ampgen/model/iFeature/PseKRAAC/type11.py
ampgen/model/iFeature/PseKRAAC/type12.py
ampgen/model/iFeature/PseKRAAC/type13.py
ampgen/model/iFeature/PseKRAAC/type14.py
ampgen/model/iFeature/PseKRAAC/type15.py
ampgen/model/iFeature/PseKRAAC/type16.py
ampgen/model/iFeature/PseKRAAC/type2.py
ampgen/model/iFeature/PseKRAAC/type3A.py
ampgen/model/iFeature/PseKRAAC/type3B.py
ampgen/model/iFeature/PseKRAAC/type4.py
ampgen/model/iFeature/PseKRAAC/type5.py
ampgen/model/iFeature/PseKRAAC/type6A.py
ampgen/model/iFeature/PseKRAAC/type6B.py
ampgen/model/iFeature/PseKRAAC/type6C.py
ampgen/model/iFeature/PseKRAAC/type7.py
ampgen/model/iFeature/PseKRAAC/type8.py
ampgen/model/iFeature/PseKRAAC/type9.py
ampgen/model/iFeature/codes/AAC.py
ampgen/model/iFeature/codes/AAINDEX.py
ampgen/model/iFeature/codes/APAAC.py
ampgen/model/iFeature/codes/ASA.py
ampgen/model/iFeature/codes/BINARY.py
ampgen/model/iFeature/codes/BLOSUM62.py
ampgen/model/iFeature/codes/CKSAAGP.py
ampgen/model/iFeature/codes/CKSAAP.py
ampgen/model/iFeature/codes/CTDC.py
ampgen/model/iFeature/codes/CTDCClass.py
ampgen/model/iFeature/codes/CTDD.py
ampgen/model/iFeature/codes/CTDDClass.py
ampgen/model/iFeature/codes/CTDT.py
ampgen/model/iFeature/codes/CTDTClass.py
ampgen/model/iFeature/codes/CTriad.py
ampgen/model/iFeature/codes/DDE.py
ampgen/model/iFeature/codes/DPC.py
ampgen/model/iFeature/codes/Disorder.py
ampgen/model/iFeature/codes/DisorderB.py
ampgen/model/iFeature/codes/DisorderC.py
ampgen/model/iFeature/codes/EAAC.py
ampgen/model/iFeature/codes/EGAAC.py
ampgen/model/iFeature/codes/GAAC.py
ampgen/model/iFeature/codes/GDPC.py
ampgen/model/iFeature/codes/GTPC.py
ampgen/model/iFeature/codes/Geary.py
ampgen/model/iFeature/codes/KNNpeptide.py
ampgen-0.1.14.dist-info/licenses/LICENSE
ampgen-0.1.14.dist-info/METADATA
ampgen-0.1.14.dist-info/WHEEL
ampgen-0.1.14.dist-info/entry_points.txt
ampgen-0.1.14.dist-info/top_level.txt
ampgen-0.1.14.dist-info/RECORD
