Metadata-Version: 2.4
Name: ampgen
Version: 0.1.14
Summary: A de novo generation pipeline leveraging evolutionary information for broad-spectrum antimicrobial peptide design
Home-page: https://github.com/yourusername/AMPGen
Author: nicholexiong
Author-email: nicholexiong <nicholexiong@example.com>
Maintainer-email: nicholexiong <nicholexiong@example.com>
License: MIT
Project-URL: Homepage, https://github.com/yourusername/AMPGen
Project-URL: Documentation, https://github.com/yourusername/AMPGen#readme
Project-URL: Repository, https://github.com/yourusername/AMPGen
Project-URL: Bug Tracker, https://github.com/yourusername/AMPGen/issues
Keywords: bioinformatics,antimicrobial-peptides,protein-design,machine-learning,evodiff
Classifier: Development Status :: 4 - Beta
Classifier: Intended Audience :: Science/Research
Classifier: Topic :: Scientific/Engineering :: Bio-Informatics
Classifier: License :: OSI Approved :: MIT License
Classifier: Programming Language :: Python :: 3
Classifier: Programming Language :: Python :: 3.8
Classifier: Programming Language :: Python :: 3.9
Classifier: Programming Language :: Python :: 3.10
Classifier: Programming Language :: Python :: 3.11
Classifier: Operating System :: OS Independent
Requires-Python: >=3.8
License-File: LICENSE
Requires-Dist: torch>=1.9.0
Requires-Dist: pandas>=1.3.0
Requires-Dist: matplotlib>=3.3.0
Requires-Dist: scikit-learn>=1.0.0
Requires-Dist: numpy>=1.21.0
Requires-Dist: biopython>=1.79
Requires-Dist: xgboost>=1.5.0
Requires-Dist: tqdm>=4.62.0
Requires-Dist: seaborn>=0.11.0
Requires-Dist: scipy>=1.7.0
Requires-Dist: joblib>=1.1.0
Requires-Dist: requests>=2.25.0
Requires-Dist: PyYAML>=6.0
Requires-Dist: click>=8.0.0
Requires-Dist: fair-esm>=2.0.0
Requires-Dist: sequence-models>=1.8.0
Requires-Dist: biotite>=1.0.0
Requires-Dist: biotraj>=1.2.0
Requires-Dist: blosum>=2.0.0
Requires-Dist: MDAnalysis>=2.0.0
Requires-Dist: mlflow>=2.0.0
Requires-Dist: networkx>=3.0.0
Requires-Dist: protobuf>=3.19.0
Requires-Dist: pyarrow>=7.0.0
Requires-Dist: SQLAlchemy>=2.0.0
Requires-Dist: Flask>=3.0.0
Requires-Dist: gunicorn>=23.0.0
Requires-Dist: docker>=7.0.0
Requires-Dist: gitpython>=3.1.0
Requires-Dist: mrcfile>=1.5.0
Requires-Dist: mmtf-python>=1.1.0
Requires-Dist: pdb-tools>=2.5.0
Requires-Dist: GridDataFormats>=1.0.0
Requires-Dist: mda-xdrlib>=0.2.0
Requires-Dist: opentelemetry-api>=1.27.0
Requires-Dist: opentelemetry-sdk>=1.27.0
Requires-Dist: opentelemetry-semantic-conventions>=0.48b0
Requires-Dist: databricks-sdk>=0.32.0
Requires-Dist: graphene>=3.3.0
Requires-Dist: graphql-core>=3.2.0
Requires-Dist: graphql-relay>=3.2.0
Requires-Dist: greenlet>=3.1.0
Requires-Dist: mako>=1.3.0
Requires-Dist: markdown>=3.7.0
Requires-Dist: msgpack>=1.1.0
Requires-Dist: pyasn1>=0.6.0
Requires-Dist: pyasn1_modules>=0.4.0
Requires-Dist: pyparsing>=3.1.0
Requires-Dist: pysocks>=1.7.0
Requires-Dist: python-dateutil>=2.9.0
Requires-Dist: pytz>=2024.2
Requires-Dist: rsa>=4.9.0
Requires-Dist: six>=1.16.0
Requires-Dist: sqlparse>=0.5.0
Requires-Dist: sympy>=1.13.0
Requires-Dist: threadpoolctl>=3.5.0
Requires-Dist: typing_extensions>=4.12.0
Requires-Dist: tzdata>=2024.1
Requires-Dist: urllib3>=2.2.0
Requires-Dist: werkzeug>=3.0.0
Requires-Dist: wrapt>=1.16.0
Requires-Dist: zipp>=3.20.0
Requires-Dist: alembic>=1.13.0
Requires-Dist: aniso8601>=9.0.0
Requires-Dist: blinker>=1.8.0
Requires-Dist: brotli>=1.0.0
Requires-Dist: cachetools>=5.5.0
Requires-Dist: certifi>=2024.8.0
Requires-Dist: charset-normalizer>=3.3.0
Requires-Dist: cloudpickle>=3.0.0
Requires-Dist: contourpy>=1.3.0
Requires-Dist: cycler>=0.12.0
Requires-Dist: deprecated>=1.2.0
Requires-Dist: fasteners>=0.19.0
Requires-Dist: filelock>=3.13.0
Requires-Dist: fonttools>=4.53.0
Requires-Dist: gitdb>=4.0.0
Requires-Dist: gmpy2
Requires-Dist: google-auth>=2.34.0
Requires-Dist: idna>=3.10.0
Requires-Dist: importlib_metadata>=8.4.0
Requires-Dist: itsdangerous>=2.2.0
Requires-Dist: jinja2>=3.1.0
Requires-Dist: kiwisolver>=1.4.0
Requires-Dist: lmdb>=1.5.0
Requires-Dist: markupsafe>=2.1.0
Requires-Dist: mlflow-skinny>=2.16.0
Requires-Dist: mpmath>=1.3.0
Requires-Dist: packaging>=24.1.0
Requires-Dist: pillow>=10.4.0
Requires-Dist: pyyaml>=6.0.0
Requires-Dist: requests>=2.32.0
Requires-Dist: smmap>=5.0.0
Provides-Extra: dev
Requires-Dist: pytest>=6.0; extra == "dev"
Requires-Dist: pytest-cov>=2.0; extra == "dev"
Requires-Dist: black>=21.0; extra == "dev"
Requires-Dist: flake8>=3.8; extra == "dev"
Requires-Dist: mypy>=0.800; extra == "dev"
Dynamic: author
Dynamic: home-page
Dynamic: license-file
Dynamic: requires-python
